libsimba/__init__.py
libsimba/auth/__init__.py
libsimba/auth/client_credentials.py
libsimba/auth/password.py
libsimba/auth/pkce.py
libsimba/base/wallet_base.py
libsimba/class_converter.py
libsimba/decorators.py
libsimba/exceptions.py
libsimba/file_handler.py
libsimba/param_checking_contract.py
libsimba/settings.py
libsimba/simba.py
libsimba/simba_async.py
libsimba/simba_contract.py
libsimba/simba_contract_async.py
libsimba/simba_hinted_contract.py
libsimba/simba_request.py
libsimba/simba_wallet.py
libsimba/templates/__init__.py
libsimba/templates/contract.tpl
libsimba/utils.py
libsimba.py_platform-0.1.6.dist-info/entry_points.txt
libsimba.py_platform-0.1.6.dist-info/LICENSE
libsimba.py_platform-0.1.6.dist-info/WHEEL
libsimba.py_platform-0.1.6.dist-info/METADATA
libsimba.py_platform-0.1.6.dist-info/RECORD
